lightai/commons/__init__.py
lightai/commons/_definitions.py
lightai/commons/_utils.py
lightai/training/__init__.py
lightai-0.0.1.dist-info/LICENSE
lightai-0.0.1.dist-info/METADATA
lightai-0.0.1.dist-info/WHEEL
lightai-0.0.1.dist-info/top_level.txt
lightai-0.0.1.dist-info/RECORD
