Metadata-Version: 2.1
Name: lightai
Version: 0.0.1
Summary: UNKNOWN
Home-page: UNKNOWN
Author: Marouen Azzouz, Youssef Azzouz
Author-email: azzouz.marouen@gmail.com, youssef.azzouz1512@gmail.com
License: UNKNOWN
Platform: UNKNOWN
Requires-Dist: flask (==1.1.2)
Requires-Dist: flask-restful
Requires-Dist: pillow
Requires-Dist: PIL
Requires-Dist: wordcloud
Requires-Dist: matplotlib
Provides-Extra: train
